svg_matrix/__init__.py
svg_matrix/_runtime.py
svg_matrix/cli.py
svg_matrix/conversion.py
svg_matrix/library.py
svg_matrix/optimization.py
svg_matrix/validation.py
svg_matrix-1.3.15.dist-info/METADATA
svg_matrix-1.3.15.dist-info/WHEEL
svg_matrix-1.3.15.dist-info/entry_points.txt
svg_matrix-1.3.15.dist-info/licenses/LICENSE
svg_matrix-1.3.15.dist-info/RECORD
