Metadata-Version: 2.4
Name: svg-matrix
Version: 1.3.15
Summary: Python wrapper for svg-matrix - arbitrary-precision SVG optimization, validation, and manipulation
Project-URL: Homepage, https://github.com/Emasoft/svg-matrix-python
Project-URL: Repository, https://github.com/Emasoft/svg-matrix-python
Project-URL: Documentation, https://github.com/Emasoft/SVG-MATRIX#readme
Project-URL: Issues, https://github.com/Emasoft/svg-matrix-python/issues
Author-email: Emasoft <713559+Emasoft@users.noreply.github.com>
License-Expression: MIT
License-File: LICENSE
Keywords: graphics,inkscape,matrix,optimization,svg,svgo,transform,validation,vector
Classifier: Development Status :: 4 - Beta
Classifier: Intended Audience :: Developers
Classifier: License :: OSI Approved :: MIT License
Classifier: Operating System :: OS Independent
Classifier: Programming Language :: Python :: 3
Classifier: Programming Language :: Python :: 3.9
Classifier: Programming Language :: Python :: 3.10
Classifier: Programming Language :: Python :: 3.11
Classifier: Programming Language :: Python :: 3.12
Classifier: Programming Language :: Python :: 3.13
Classifier: Topic :: Multimedia :: Graphics
Classifier: Topic :: Multimedia :: Graphics :: Graphics Conversion
Classifier: Topic :: Software Development :: Libraries :: Python Modules
Requires-Python: >=3.9
Provides-Extra: dev
Requires-Dist: bandit>=1.7.0; extra == 'dev'
Requires-Dist: mypy>=1.10.0; extra == 'dev'
Requires-Dist: pytest-asyncio>=0.23; extra == 'dev'
Requires-Dist: pytest>=8.0; extra == 'dev'
Requires-Dist: ruff>=0.4.0; extra == 'dev'
Provides-Extra: test
Requires-Dist: pytest-asyncio>=0.23; extra == 'test'
Requires-Dist: pytest>=8.0; extra == 'test'
